{"v":"4.8.0","meta":{"g":"LottieFiles AE 2.0.4","a":"","k":"","d":"","tc":""},"fr":30,"ip":0,"op":150,"w":378,"h":539,"nm":"Woman Weight Long","ddd":0,"assets":[],"layers":[{"ddd":0,"ind":1,"ty":4,"nm":"5 Hair Outlines","sr":1,"ks":{"o":{"a":0,"k":100,"ix":11},"r":{"a":0,"k":0,"ix":10},"p":{"a":0,"k":[192.923,52.293,0],"ix":2},"a":{"a":0,"k":[11.28,7.53,0],"ix":1},"s":{"a":0,"k":[172.099,172.099,100],"ix":6}},"ao":0,"shapes":[{"ty":"gr","it":[{"ind":0,"ty":"sh","ix":1,"ks":{"a":0,"k":{"i":[[-0.4,-6.95],[1.8,-1.34],[-3.65,0.04]],"o":[[-1.34,-6.71],[2.07,-1.81],[9.39,0.12]],"v":[[12.011,7.28],[-11.03,-4.074],[-2.421,-8.587]],"c":true},"ix":2},"nm":"Path 1","mn":"ADBE Vector Shape - Group","hd":false},{"ty":"mm","mm":4,"nm":"Merge Paths 1","mn":"ADBE Vector Filter - Merge","hd":false},{"ty":"fl","c":{"a":0,"k":[0.149019607843,0.149019607843,0.149019607843,1],"ix":4},"o":{"a":0,"k":100,"ix":5},"r":1,"bm":0,"nm":"Fill 1","mn":"ADBE Vector Graphic - Fill","hd":false},{"ty":"tr","p":{"a":0,"k":[11.28,7.53],"ix":2},"a":{"a":0,"k":[0,0],"ix":1},"s":{"a":0,"k":[100,100],"ix":3},"r":{"a":0,"k":0,"ix":6},"o":{"a":0,"k":100,"ix":7},"sk":{"a":0,"k":0,"ix":4},"sa":{"a":0,"k":0,"ix":5},"nm":"Transform"}],"nm":"Group 1","np":3,"cix":2,"bm":0,"ix":1,"mn":"ADBE Vector Group","hd":false}],"ip":0,"op":155,"st":47,"bm":0},{"ddd":0,"ind":2,"ty":4,"nm":"1 Face Outlines","sr":1,"ks":{"o":{"a":0,"k":100,"ix":11},"r":{"a":0,"k":0,"ix":10},"p":{"a":0,"k":[188.999,70.023,0],"ix":2},"a":{"a":0,"k":[17.303,19.342,0],"ix":1},"s":{"a":1,"k":[{"i":{"x":[0.833,0.833,0.833],"y":[0.833,0.833,0.833]},"o":{"x":[0.167,0.167,0.167],"y":[0.167,0.167,0.167]},"t":0,"s":[150,150,100]},{"i":{"x":[0.833,0.833,0.833],"y":[0.833,0.833,0.833]},"o":{"x":[0.167,0.167,0.167],"y":[0.167,0.167,0.167]},"t":32.831,"s":[144,150,100]},{"t":149,"s":[144,150,100]}],"ix":6}},"ao":0,"shapes":[{"ty":"gr","it":[{"ind":0,"ty":"sh","ix":1,"ks":{"a":1,"k":[{"i":{"x":0.667,"y":1},"o":{"x":0.333,"y":0},"t":0,"s":[{"i":[[0.638,1.497],[0.459,-0.451],[0,0.826],[9.923,0.12],[0,-7.262],[0.065,-0.692],[0.426,-1.002],[-0.852,-1.255],[-0.489,-2.123],[-1.768,-1.289],[-2.412,0.253],[-2.515,1.832],[-1.012,4.397],[0.282,1.669]],"o":[[-0.427,-1.002],[-0.065,-0.692],[0,-7.262],[-9.922,0.12],[0,0.826],[-0.459,-0.451],[-0.639,1.497],[-0.282,1.669],[1.012,4.397],[2.515,1.832],[2.413,0.253],[1.768,-1.289],[0.488,-2.123],[0.852,-1.254]],"v":[[16.415,-2.775],[14.698,-2.717],[14.589,-4.977],[0,-19.092],[-14.588,-4.977],[-14.697,-2.717],[-16.414,-2.775],[-15.379,1.638],[-15.316,7.02],[-8.996,15.997],[0,18.84],[8.997,15.997],[15.317,7.02],[15.38,1.638]],"c":true}]},{"i":{"x":0.833,"y":0.934},"o":{"x":0.333,"y":0},"t":32.831,"s":[{"i":[[0.638,1.497],[0.459,-0.451],[0,0.826],[9.923,0.12],[0,-7.262],[0.065,-0.692],[0.426,-1.002],[-0.852,-1.255],[-0.489,-2.123],[-1.768,-1.289],[-2.7,-0.032],[-2.515,1.832],[-1.012,4.397],[0.282,1.669]],"o":[[-0.427,-1.002],[-0.065,-0.692],[0,-7.262],[-9.922,0.12],[0,0.826],[-0.459,-0.451],[-0.639,1.497],[-0.282,1.669],[1.012,4.397],[2.515,1.832],[2.801,-0.125],[1.768,-1.289],[0.488,-2.123],[0.852,-1.254]],"v":[[16.415,-2.775],[14.698,-2.717],[14.589,-4.977],[0,-19.092],[-14.588,-4.977],[-14.697,-2.717],[-16.414,-2.775],[-15.379,1.638],[-15.316,7.02],[-8.996,15.997],[-0.001,18.527],[8.997,15.997],[15.317,7.02],[15.38,1.638]],"c":true}]},{"i":{"x":0.833,"y":0.934},"o":{"x":0.167,"y":0.066},"t":85.864,"s":[{"i":[[0.638,1.497],[0.459,-0.451],[0,0.826],[9.923,0.12],[0,-7.262],[0.065,-0.692],[0.426,-1.002],[-0.852,-1.255],[-0.643,-1.831],[-1.768,-1.289],[-2.7,-0.032],[-2.269,2.113],[-1.964,3.693],[-0.168,1.822]],"o":[[-0.427,-1.002],[-0.065,-0.692],[0,-7.262],[-9.922,0.12],[0,0.826],[-0.459,-0.451],[-0.639,1.497],[0.08,1.959],[1.397,3.979],[2.515,1.832],[2.801,-0.125],[1.644,-1.537],[0.547,-1.175],[0.852,-1.254]],"v":[[16.415,-2.775],[14.698,-2.717],[14.589,-4.977],[0,-19.092],[-14.588,-4.977],[-14.697,-2.717],[-16.414,-2.775],[-14.239,1.911],[-13.256,6.451],[-7.462,13.703],[0.109,17.096],[8.077,13.177],[13.191,6.451],[14.46,2.079]],"c":true}]},{"t":149,"s":[{"i":[[0.638,1.497],[0.459,-0.451],[0,0.826],[9.923,0.12],[0,-7.262],[0.065,-0.692],[0.426,-1.002],[-0.852,-1.255],[-0.574,-1.54],[-1.645,-1.43],[-3.746,-0.093],[-2.006,2.196],[-2.192,3.524],[-0.446,1.794]],"o":[[-0.427,-1.002],[-0.065,-0.692],[0,-7.262],[-9.922,0.12],[0,0.826],[-0.459,-0.451],[-0.639,1.497],[0.563,1.909],[1.364,3.635],[2.211,1.899],[3.621,-0.079],[1.518,-1.679],[0.608,-1.052],[0.939,-1.106]],"v":[[16.415,-2.775],[14.698,-2.717],[14.589,-4.977],[0,-19.092],[-14.588,-4.977],[-14.697,-2.717],[-16.414,-2.775],[-13.966,1.977],[-12.601,6.269],[-7.512,13.169],[0.151,16.892],[7.984,12.578],[12.681,6.315],[14.239,2.185]],"c":true}]}],"ix":2},"nm":"Path 1","mn":"ADBE Vector Shape - Group","hd":false},{"ty":"mm","mm":4,"nm":"Merge Paths 1","mn":"ADBE Vector Filter - Merge","hd":false},{"ty":"fl","c":{"a":0,"k":[1,0.807843197093,0.666666666667,1],"ix":4},"o":{"a":0,"k":100,"ix":5},"r":1,"bm":0,"nm":"Fill 1","mn":"ADBE Vector Graphic - Fill","hd":false},{"ty":"tr","p":{"a":0,"k":[17.303,19.343],"ix":2},"a":{"a":0,"k":[0,0],"ix":1},"s":{"a":0,"k":[100,100],"ix":3},"r":{"a":0,"k":0,"ix":6},"o":{"a":0,"k":100,"ix":7},"sk":{"a":0,"k":0,"ix":4},"sa":{"a":0,"k":0,"ix":5},"nm":"Transform"}],"nm":"Group 1","np":3,"cix":2,"bm":0,"ix":1,"mn":"ADBE Vector Group","hd":false}],"ip":0,"op":155,"st":0,"bm":0},{"ddd":0,"ind":3,"ty":4,"nm":"shad","sr":1,"ks":{"o":{"a":0,"k":10,"ix":11},"r":{"a":0,"k":0,"ix":10},"p":{"a":0,"k":[189,365,0],"ix":2},"a":{"a":0,"k":[0,0,0],"ix":1},"s":{"a":0,"k":[150,150,100],"ix":6}},"ao":0,"shapes":[{"ty":"gr","it":[{"ind":0,"ty":"sh","ix":1,"ks":{"a":1,"k":[{"i":{"x":0.833,"y":0.833},"o":{"x":0.167,"y":0.167},"t":0,"s":[{"i":[[0,0],[0,0],[-16.379,0.58]],"o":[[0,0],[0,0],[15.875,-0.562]],"v":[[11.875,-186.75],[-11.938,-186.25],[0.312,-173.5]],"c":true}]},{"i":{"x":0.833,"y":0.833},"o":{"x":0.167,"y":0.167},"t":32.831,"s":[{"i":[[0,0],[0,0],[-13.625,0.625]],"o":[[0,0],[0,0],[12.994,-0.596]],"v":[[10.812,-187.188],[-10.625,-186.25],[0.562,-174.625]],"c":true}]},{"i":{"x":0.667,"y":1},"o":{"x":0.167,"y":0.167},"t":63.136,"s":[{"i":[[0,0],[0,0],[-11.062,-0.062]],"o":[[0,0],[0,0],[10.002,0.057]],"v":[[13.188,-187.125],[-13.062,-186.812],[0.562,-176.75]],"c":true}]},{"t":95.966796875,"s":[{"i":[[0,0],[0,0],[-11.457,0.148]],"o":[[0,0],[0,0],[10.993,-0.142]],"v":[[12.191,-190.757],[-12.701,-192.257],[0.457,-177.711]],"c":true}]}],"ix":2},"nm":"Path 1","mn":"ADBE Vector Shape - Group","hd":false},{"ty":"st","c":{"a":0,"k":[0.894118006089,0.090195996154,0.282353001015,1],"ix":3},"o":{"a":0,"k":100,"ix":4},"w":{"a":0,"k":0,"ix":5},"lc":1,"lj":1,"ml":4,"bm":0,"nm":"Stroke 1","mn":"ADBE Vector Graphic - Stroke","hd":false},{"ty":"fl","c":{"a":0,"k":[0.137254901961,0.074509803922,0,1],"ix":4},"o":{"a":0,"k":100,"ix":5},"r":1,"bm":0,"nm":"Fill 1","mn":"ADBE Vector Graphic - Fill","hd":false},{"ty":"tr","p":{"a":0,"k":[0,0],"ix":2},"a":{"a":0,"k":[0,0],"ix":1},"s":{"a":0,"k":[100,100],"ix":3},"r":{"a":0,"k":0,"ix":6},"o":{"a":0,"k":100,"ix":7},"sk":{"a":0,"k":0,"ix":4},"sa":{"a":0,"k":0,"ix":5},"nm":"Transform"}],"nm":"Shape 1","np":3,"cix":2,"bm":0,"ix":1,"mn":"ADBE Vector Group","hd":false}],"ip":0,"op":155,"st":0,"bm":0},{"ddd":0,"ind":4,"ty":4,"nm":"1 Cloth Shadow Outlines","sr":1,"ks":{"o":{"a":0,"k":100,"ix":11},"r":{"a":0,"k":0,"ix":10},"p":{"a":1,"k":[{"i":{"x":0.833,"y":0.833},"o":{"x":0.167,"y":0.167},"t":0,"s":[189,171.901,0],"to":[0,-0.633,0],"ti":[0,1.402,0]},{"i":{"x":0.467,"y":0.847},"o":{"x":0.508,"y":0.382},"t":32.831,"s":[189,174.323,0],"to":[0,-3.241,0],"ti":[0,1.903,0]},{"t":149,"s":[188.999,165.303,0]}],"ix":2},"a":{"a":0,"k":[46.906,25.744,0],"ix":1},"s":{"a":1,"k":[{"i":{"x":[0.833,0.833,0.833],"y":[0.833,0.833,0.833]},"o":{"x":[0.167,0.167,0.167],"y":[0.167,0.167,0.167]},"t":0,"s":[149.303,154.661,100]},{"i":{"x":[0.833,0.833,0.833],"y":[0.833,0.833,0.833]},"o":{"x":[0.167,0.167,0.167],"y":[0.167,0.167,0.167]},"t":32.831,"s":[133.611,145.628,100]},{"i":{"x":[0.833,0.833,0.833],"y":[0.833,0.833,0.833]},"o":{"x":[0.167,0.167,0.167],"y":[0.167,0.167,0.167]},"t":63.136,"s":[108.409,132.033,100]},{"i":{"x":[0.572,0.572,0.572],"y":[0.681,0.377,-2.286]},"o":{"x":[0.19,0.19,0.19],"y":[0.17,0.331,1.749]},"t":95.967,"s":[100.94,100.031,100]},{"t":149,"s":[82.466,89.992,100]}],"ix":6}},"ao":0,"shapes":[{"ty":"gr","it":[{"ind":0,"ty":"sh","ix":1,"ks":{"a":0,"k":{"i":[[0,0]],"o":[[0,0]],"v":[[-118.059,61.676]],"c":false},"ix":2},"nm":"Path 1","mn":"ADBE Vector Shape - Group","hd":false},{"ty":"st","c":{"a":0,"k":[0.894118006089,0.090195996154,0.282353001015,1],"ix":3},"o":{"a":0,"k":100,"ix":4},"w":{"a":0,"k":10,"ix":5},"lc":1,"lj":1,"ml":4,"bm":0,"nm":"Stroke 1","mn":"ADBE Vector Graphic - Stroke","hd":false},{"ty":"fl","c":{"a":0,"k":[0.407843137255,0.03137254902,0.643137254902,1],"ix":4},"o":{"a":0,"k":100,"ix":5},"r":1,"bm":0,"nm":"Fill 1","mn":"ADBE Vector Graphic - Fill","hd":false},{"ty":"tr","p":{"a":0,"k":[0,0],"ix":2},"a":{"a":0,"k":[0,0],"ix":1},"s":{"a":0,"k":[100,100],"ix":3},"r":{"a":0,"k":0,"ix":6},"o":{"a":0,"k":100,"ix":7},"sk":{"a":0,"k":0,"ix":4},"sa":{"a":0,"k":0,"ix":5},"nm":"Transform"}],"nm":"Shape 1","np":3,"cix":2,"bm":0,"ix":1,"mn":"ADBE Vector Group","hd":false},{"ty":"gr","it":[{"ind":0,"ty":"sh","ix":1,"ks":{"a":1,"k":[{"i":{"x":0.833,"y":0.833},"o":{"x":0.167,"y":0.167},"t":0,"s":[{"i":[[-2.34,3.425],[3.694,6.449],[10.697,-3.834],[11.31,0.204],[0,0],[12.227,4.382],[-3.25,5.948],[-8.659,-12.672],[1.581,-9.969],[0,0],[-6.695,-1.538],[-16.095,0.875],[0,0],[-13.864,3.184],[-6.646,-12.386],[0,0]],"o":[[8.659,-12.672],[3.25,5.948],[-12.226,4.382],[0,0],[-11.31,0.204],[-10.696,-3.834],[-3.694,6.449],[2.34,3.425],[0,0],[2.628,-9.234],[13.864,3.184],[0,0],[16.095,0.875],[6.695,-1.538],[0,0],[-3.13,-10.818]],"v":[[43.251,4.285],[39.252,-25.744],[37.386,-2.637],[0.222,-7.271],[-0.222,-7.271],[-37.387,-2.637],[-39.252,-25.744],[-43.251,4.285],[-45.535,19.287],[-46.749,26.593],[-36.837,7.338],[-0.222,-2.875],[0.222,-2.875],[36.837,7.338],[48.214,25.583],[45.954,18.438]],"c":true}]},{"i":{"x":0.833,"y":0.833},"o":{"x":0.167,"y":0.167},"t":32.831,"s":[{"i":[[-0.83,3.171],[3.694,6.449],[10.697,-3.834],[11.31,0.204],[0,0],[12.227,4.382],[-3.25,5.948],[-8.659,-12.672],[0.951,-9.56],[0,0],[-6.695,-1.538],[-16.095,0.875],[0,0],[-13.864,3.184],[-3.482,-9.946],[0,0]],"o":[[8.659,-12.672],[3.25,5.948],[-12.226,4.382],[0,0],[-11.31,0.204],[-10.696,-3.834],[-3.694,6.449],[2.34,3.425],[0,0],[2.292,-11.201],[13.864,3.184],[0,0],[16.095,0.875],[6.695,-1.538],[0,0],[-1.977,-8.904]],"v":[[43.851,4.58],[39.252,-25.744],[37.386,-2.637],[0.222,-7.271],[-0.222,-7.271],[-37.387,-2.637],[-39.252,-25.744],[-45.43,4.413],[-47.111,19.587],[-48.582,30.486],[-36.837,7.338],[-0.222,-2.875],[0.222,-2.875],[36.837,7.338],[48.716,28.136],[46.791,15.763]],"c":true}]},{"i":{"x":0.833,"y":0.833},"o":{"x":0.167,"y":0.167},"t":63.136,"s":[{"i":[[0.564,2.936],[3.694,6.449],[10.697,-3.834],[11.31,0.204],[0,0],[12.227,4.382],[-3.25,5.948],[-8.659,-12.672],[1.829,-9.587],[0,0],[-6.695,-1.538],[-16.095,0.875],[0,0],[-13.864,3.184],[-1.45,-11.142],[0,0]],"o":[[8.659,-12.672],[3.25,5.948],[-12.226,4.382],[0,0],[-11.31,0.204],[-10.696,-3.834],[-3.694,6.449],[2.34,3.425],[0,0],[3.07,-11.255],[13.864,3.184],[0,0],[16.095,0.875],[6.695,-1.538],[0,0],[0,-9.53]],"v":[[44.404,4.853],[39.252,-25.744],[37.386,-2.637],[0.222,-7.271],[-0.222,-7.271],[-37.387,-2.637],[-39.252,-25.744],[-47.442,4.531],[-51.006,19.296],[-52.846,30.158],[-36.837,7.338],[-0.222,-2.875],[0.222,-2.875],[36.837,7.338],[52.204,27.537],[51.47,20.113]],"c":true}]},{"i":{"x":0.833,"y":0.833},"o":{"x":0.167,"y":0.167},"t":85.864,"s":[{"i":[[0.85,2.888],[3.694,6.449],[10.697,-3.834],[11.31,0.204],[0,0],[12.227,4.382],[-3.25,5.948],[-8.659,-12.672],[0.563,-9.548],[0,0],[-6.695,-1.538],[-16.095,0.875],[0,0],[-13.864,3.184],[-2.971,-11.293],[0,0]],"o":[[8.659,-12.672],[3.25,5.948],[-12.226,4.382],[0,0],[-11.31,0.204],[-10.696,-3.834],[-3.694,6.449],[2.34,3.425],[0,0],[3.23,-11.267],[13.864,3.184],[0,0],[16.095,0.875],[6.695,-1.538],[0,0],[0,-9.53]],"v":[[44.978,5.166],[39.736,-20.966],[37.386,-2.637],[0.222,-7.271],[-0.222,-7.271],[-37.387,-2.637],[-38.889,-23.355],[-45.621,4.742],[-47.35,19.333],[-48.187,29.51],[-36.837,7.338],[-0.222,-2.875],[0.222,-2.875],[36.837,7.338],[48.352,28.572],[47.996,19.354]],"c":true}]},{"i":{"x":0.833,"y":0.833},"o":{"x":0.167,"y":0.167},"t":95.967,"s":[{"i":[[0.977,2.866],[3.694,6.449],[10.697,-3.834],[11.31,0.204],[0,0],[12.227,4.382],[-3.25,5.948],[-8.659,-12.672],[0,-9.53],[0,0],[-6.695,-1.538],[-16.095,0.875],[0,0],[-13.864,3.184],[-4.55,-9.392],[0,0]],"o":[[8.659,-12.672],[3.25,5.948],[-12.226,4.382],[0,0],[-11.31,0.204],[-10.696,-3.834],[-3.694,6.449],[2.34,3.425],[0,0],[3.301,-11.272],[13.864,3.184],[0,0],[16.095,0.875],[6.695,-1.538],[0,0],[-1.31,-8.109]],"v":[[45.232,5.306],[38.385,-24.869],[37.386,-2.637],[0.222,-7.271],[-0.222,-7.271],[-37.387,-2.637],[-38.633,-25.744],[-44.811,4.836],[-46.688,18.08],[-47.202,28.394],[-36.837,7.338],[-0.222,-2.875],[0.222,-2.875],[36.837,7.338],[47.398,28.547],[46.263,19.017]],"c":true}]},{"i":{"x":0.833,"y":0.833},"o":{"x":0.167,"y":0.167},"t":121,"s":[{"i":[[-0.602,3.132],[3.694,6.449],[10.697,-3.834],[11.31,0.204],[0,0],[12.227,4.382],[-2.499,7.409],[-8.659,-12.672],[0,-9.53],[0,0],[-6.695,-1.538],[-16.095,0.875],[0,0],[-13.864,3.184],[-2.601,-11.256],[0,0]],"o":[[8.659,-12.672],[3.25,5.948],[-12.226,4.382],[0,0],[-11.31,0.204],[-10.696,-3.834],[-3.694,6.449],[2.34,3.425],[0,0],[2.42,-11.21],[13.864,3.184],[0,0],[16.095,0.875],[6.695,-1.538],[0,0],[0,-9.53]],"v":[[44.506,5.084],[39.117,-26.414],[37.386,-2.637],[0.222,-7.271],[-0.222,-7.271],[-37.387,-2.637],[-39.505,-27.265],[-44.104,4.706],[-47.386,19.883],[-47.843,27.626],[-36.837,7.338],[-0.222,-2.875],[0.222,-2.875],[36.837,7.338],[46.786,27.215],[47.178,19.992]],"c":true}]},{"t":149,"s":[{"i":[[-2.34,3.425],[3.694,6.449],[10.697,-3.834],[11.31,0.204],[0,0],[12.227,4.382],[-1.673,9.017],[-8.659,-12.672],[0,-9.53],[0,0],[-6.695,-1.538],[-16.095,0.875],[0,0],[-13.864,3.184],[-1.45,-11.142],[0,0]],"o":[[8.659,-12.672],[3.25,5.948],[-12.226,4.382],[0,0],[-11.31,0.204],[-10.696,-3.834],[-3.694,6.449],[2.34,3.425],[0,0],[1.45,-11.142],[13.864,3.184],[0,0],[16.095,0.875],[6.695,-1.538],[0,0],[0,-9.53]],"v":[[43.706,4.84],[41.071,-28.661],[37.386,-2.637],[0.222,-7.271],[-0.222,-7.271],[-37.387,-2.637],[-40.465,-28.939],[-43.327,4.563],[-46.518,18.842],[-47.049,26.231],[-36.837,7.338],[-0.222,-2.875],[0.222,-2.875],[36.837,7.338],[46.746,26.3],[46.822,21.065]],"c":true}]}],"ix":2},"nm":"Path 1","mn":"ADBE Vector Shape - Group","hd":false},{"ty":"mm","mm":4,"nm":"Merge Paths 1","mn":"ADBE Vector Filter - Merge","hd":false},{"ty":"fl","c":{"a":0,"k":[0.407843137255,0.03137254902,0.643137254902,1],"ix":4},"o":{"a":0,"k":100,"ix":5},"r":1,"bm":0,"nm":"Fill 1","mn":"ADBE Vector Graphic - Fill","hd":false},{"ty":"tr","p":{"a":0,"k":[46.906,25.745],"ix":2},"a":{"a":0,"k":[0,0],"ix":1},"s":{"a":0,"k":[100,100],"ix":3},"r":{"a":0,"k":0,"ix":6},"o":{"a":0,"k":100,"ix":7},"sk":{"a":0,"k":0,"ix":4},"sa":{"a":0,"k":0,"ix":5},"nm":"Transform"}],"nm":"Group 1","np":3,"cix":2,"bm":0,"ix":2,"mn":"ADBE Vector Group","hd":false}],"ip":0,"op":155,"st":0,"bm":0},{"ddd":0,"ind":5,"ty":4,"nm":"Cloth","sr":1,"ks":{"o":{"a":0,"k":100,"ix":11},"r":{"a":0,"k":0,"ix":10},"p":{"a":0,"k":[189,365,0],"ix":2},"a":{"a":0,"k":[0,0,0],"ix":1},"s":{"a":0,"k":[150,150,100],"ix":6}},"ao":0,"shapes":[{"ty":"gr","it":[{"ind":0,"ty":"sh","ix":1,"ks":{"a":1,"k":[{"i":{"x":0.833,"y":0.833},"o":{"x":0.167,"y":0.167},"t":0,"s":[{"i":[[0,0],[0,0],[0,0],[-0.562,-5.938],[0.375,-2.5],[3.5,-9.625],[0.121,-0.599],[-10.847,-15.257],[-16.75,0],[0,0],[-4.458,38.208],[3.375,7],[3.625,10.875],[0.559,0.197],[0.005,0],[0,0],[16.875,0]],"o":[[0,0],[0,0],[0,0],[0.886,9.354],[0.375,2.812],[-0.163,0.447],[-3.267,16.152],[12.25,-7.25],[16.75,0],[0,0],[1.486,-12.737],[2.25,-3.875],[-3.59,-10.771],[-0.005,-0.002],[-0.5,0],[0,0],[-16.875,0]],"v":[[-23.719,-172.354],[-32.024,-170.496],[-36.292,-169.542],[-44.25,-140.875],[-42.625,-123.125],[-51.5,-85.396],[-52.067,-82.986],[-33.125,-12.125],[0.438,-23.5],[33.125,-12.875],[53.125,-73.375],[40.125,-124.625],[43,-148.25],[37.828,-169.497],[30.208,-171.312],[23.833,-172.542],[1.375,-161.125]],"c":true}]},{"i":{"x":0.833,"y":0.833},"o":{"x":0.167,"y":0.167},"t":33,"s":[{"i":[[0,0],[0,0],[0,0],[2.559,-10.324],[0.375,-2.5],[2.467,-9.704],[0.101,-0.742],[-11.163,-15.108],[-16.75,0],[0,0],[-1.083,43.116],[3.856,9.074],[3.168,10.027],[2.488,0.843],[0.005,0],[0,0],[16.875,0]],"o":[[0,0],[0,0],[0,0],[-0.656,9.239],[-0.687,4.129],[-0.129,0.629],[-2.071,15.225],[9.79,-6.32],[16.756,0],[0,0],[0.339,-13.438],[3.256,-4.019],[-3.287,-10.837],[-0.005,-0.002],[-0.5,0],[0,0],[-16.875,0]],"v":[[-17.595,-173.048],[-30.445,-170.341],[-33.878,-169.87],[-39.003,-143.317],[-37.893,-124.685],[-45.769,-88.072],[-46.114,-86.013],[-33.1,-17.863],[0.657,-29.251],[34.902,-18.971],[46.228,-79.311],[36.103,-125.966],[37.693,-146.91],[35.387,-169.593],[32.566,-170.85],[21.381,-173.261],[1.375,-161.125]],"c":true}]},{"i":{"x":0.833,"y":0.833},"o":{"x":0.167,"y":0.167},"t":63,"s":[{"i":[[0,0],[0,0],[0,0],[3.961,-9.033],[0.375,-2.5],[2.087,-9.732],[0.088,-0.699],[-8.478,-13.917],[-16.75,0.049],[0,0],[0.775,43.065],[4.249,10.445],[3.429,6.742],[0.435,0.229],[0.005,0],[0,0],[16.875,0]],"o":[[0,0],[0,0],[0,0],[-3.737,10.228],[-1.923,4.479],[-0.108,0.589],[-1.817,14.353],[8.325,-5.009],[17.764,-0.054],[0,0],[-0.013,-13.713],[3.675,-4.079],[-3.939,-8.981],[-0.004,-0.002],[-0.5,0],[0,0],[-16.875,0]],"v":[[-17.879,-173.017],[-27.065,-171.686],[-31.157,-170.316],[-33.464,-148.329],[-32.497,-126.138],[-40.05,-92.92],[-40.345,-90.986],[-31.296,-26.207],[0.762,-35.651],[31.625,-26.982],[40.493,-84.376],[31.252,-127.751],[32.806,-146.655],[31.065,-169.963],[28.404,-171.139],[20.476,-173.508],[1.375,-161.125]],"c":true}]},{"i":{"x":0.833,"y":0.833},"o":{"x":0.167,"y":0.167},"t":86,"s":[{"i":[[0,0],[0,0],[0,0],[4.54,-7.656],[0.375,-2.5],[1.797,-9.753],[0.088,-0.646],[-8.403,-14.752],[-16.75,0.086],[0,0],[2.706,47.348],[4.55,11.496],[3.624,4.242],[0.349,0.229],[0.005,0],[0,0],[16.875,0]],"o":[[0,0],[0,0],[0,0],[-6.079,10.977],[-2.862,4.749],[-0.092,0.558],[-1.814,13.259],[7.201,-4.004],[18.529,-0.095],[0,0],[-0.274,-13.924],[3.996,-4.124],[-4.185,-6.463],[-0.003,-0.003],[-0.5,0],[0,0],[-16.875,0]],"v":[[-17.479,-173.651],[-25.795,-172.124],[-29.027,-171.179],[-31.675,-145.774],[-28.375,-127.254],[-35.674,-96.628],[-35.945,-94.82],[-30.229,-32.306],[0.842,-40.559],[30.164,-32.995],[36.105,-88.25],[27.546,-129.106],[30.447,-145.927],[30.142,-170.702],[26.934,-171.432],[18.449,-174.025],[1.375,-161.125]],"c":true}]},{"i":{"x":0.833,"y":0.833},"o":{"x":0.167,"y":0.167},"t":96,"s":[{"i":[[0,0],[0,0],[0,0],[4.574,-8.604],[0.375,-2.5],[1.67,-9.763],[0.082,-0.619],[-7.781,-18.219],[-16.75,0.072],[0,0],[2.341,43.358],[4.681,11.953],[3.352,4.506],[0.293,0.526],[0.01,0],[0,0],[16.875,0]],"o":[[0,0],[0,0],[0,0],[-5.605,10.643],[-2.646,4.987],[-0.085,0.545],[-1.68,12.701],[6.713,-3.566],[18.247,-0.08],[0,0],[-0.384,-14.016],[4.135,-4.144],[-4.175,-7.461],[-0.003,-0.028],[-0.5,0],[0,0],[-16.875,0]],"v":[[-17.119,-173.998],[-25.897,-172.015],[-28.694,-171.552],[-31.016,-146.042],[-27.661,-127.869],[-34.396,-97.55],[-34.647,-95.804],[-29.867,-34.645],[0.877,-42.692],[29.734,-35.385],[34.825,-89.361],[26.936,-128.794],[29.354,-145.718],[29.699,-171.423],[26.505,-171.681],[18.492,-173.931],[1.375,-161.125]],"c":true}]},{"i":{"x":0.833,"y":0.833},"o":{"x":0.167,"y":0.167},"t":114,"s":[{"i":[[0,0],[1.417,-0.25],[0,0],[4.633,-10.309],[0.375,-2.5],[1.443,-9.78],[0.071,-0.574],[-6.674,-24.354],[-16.75,0.048],[0,0],[1.713,36.242],[4.917,12.776],[2.863,4.981],[0.173,1.098],[0.019,0],[0,0],[16.875,0]],"o":[[0,0],[-1.417,0.25],[0,0],[-4.752,10.042],[-2.257,5.416],[-0.073,0.524],[-1.44,11.702],[5.834,-2.78],[17.738,-0.053],[0,0],[-0.59,-14.18],[4.387,-4.18],[-4.146,-9.216],[-0.001,-0.074],[-0.5,0],[0,0],[-16.875,0]],"v":[[-16.446,-174.442],[-28.292,-172.292],[-31.087,-170.237],[-27.746,-145.675],[-26.375,-128.974],[-32.097,-99.21],[-32.312,-97.563],[-29.197,-38.868],[0.94,-46.532],[28.948,-39.701],[32.524,-91.362],[25.822,-128.282],[27.483,-145.739],[31.218,-170.718],[28.351,-172.335],[17.054,-174.543],[1.375,-161.125]],"c":true}]},{"t":149,"s":[{"i":[[0,0],[0,0],[0,0],[4.75,-13.625],[0.375,-2.5],[1,-9.813],[0.098,-0.877],[-5.727,-26.133],[-16.75,0],[0,0],[3.292,28.75],[5.375,14.375],[1.946,5.893],[-1.77,5.928],[0.036,0],[0,0],[16.875,0]],"o":[[0,0],[0,0],[0,0],[-3.093,8.872],[-1.5,6.25],[-0.082,0.805],[-1.147,10.225],[4.125,-1.25],[16.75,0],[0,0],[-1.653,-14.44],[4.875,-4.25],[-2.875,-8.708],[0.047,-0.157],[-0.5,0],[0,0],[-16.875,0]],"v":[[-15.208,-174.781],[-21.601,-172.875],[-22.917,-172.667],[-23.75,-144.917],[-23.875,-131.125],[-27.625,-102.438],[-27.898,-99.915],[-26.177,-48.271],[1.062,-54],[26.146,-49.396],[28.292,-95.333],[22,-132.25],[24.125,-145.833],[25.583,-172.699],[23.531,-172.771],[15.75,-174.76],[1.375,-161.125]],"c":true}]}],"ix":2},"nm":"Path 1","mn":"ADBE Vector Shape - Group","hd":false},{"ty":"st","c":{"a":0,"k":[0.968627989526,0.145097994337,0.521568986481,1],"ix":3},"o":{"a":0,"k":100,"ix":4},"w":{"a":0,"k":0,"ix":5},"lc":1,"lj":1,"ml":4,"bm":0,"nm":"Stroke 1","mn":"ADBE Vector Graphic - Stroke","hd":false},{"ty":"fl","c":{"a":0,"k":[0.447058823529,0.035294117647,0.717647058824,1],"ix":4},"o":{"a":0,"k":100,"ix":5},"r":1,"bm":0,"nm":"Fill 1","mn":"ADBE Vector Graphic - Fill","hd":false},{"ty":"tr","p":{"a":0,"k":[0,0],"ix":2},"a":{"a":0,"k":[0,0],"ix":1},"s":{"a":0,"k":[100,100],"ix":3},"r":{"a":0,"k":0,"ix":6},"o":{"a":0,"k":100,"ix":7},"sk":{"a":0,"k":0,"ix":4},"sa":{"a":0,"k":0,"ix":5},"nm":"Transform"}],"nm":"Shape 1","np":3,"cix":2,"bm":0,"ix":1,"mn":"ADBE Vector Group","hd":false}],"ip":0,"op":155,"st":0,"bm":0},{"ddd":0,"ind":6,"ty":4,"nm":"1 Body Outlines","sr":1,"ks":{"o":{"a":0,"k":100,"ix":11},"r":{"a":0,"k":0,"ix":10},"p":{"a":0,"k":[189,175.37,0],"ix":2},"a":{"a":0,"k":[52.725,67.251,0],"ix":1},"s":{"a":1,"k":[{"i":{"x":[0.833,0.833,0.833],"y":[0.833,0.833,0.833]},"o":{"x":[0.167,0.167,0.167],"y":[0.167,0.167,0.167]},"t":0,"s":[150,150,100]},{"i":{"x":[0.833,0.833,0.833],"y":[0.833,0.833,0.833]},"o":{"x":[0.167,0.167,0.167],"y":[0.167,0.167,0.167]},"t":32.831,"s":[122.321,151.959,100]},{"t":149,"s":[122.321,151.959,100]}],"ix":6}},"ao":0,"shapes":[{"ty":"gr","it":[{"ind":0,"ty":"sh","ix":1,"ks":{"a":1,"k":[{"i":{"x":0.833,"y":0.833},"o":{"x":0.167,"y":0.167},"t":0,"s":[{"i":[[2.626,7.634],[0,0.526],[0,0],[-2.34,3.424],[3.384,6.338],[0,0],[2.125,8.389],[0,0],[0,0],[0,0],[0.812,-3.196],[6.623,-1.961],[0,0],[-8.988,-13.154],[-0.337,-9.895],[0,0],[2.622,-7.625],[-0.175,-4.599],[-37.417,-3.108],[-0.466,12.246]],"o":[[-2.623,-7.625],[0,0],[0.026,-10.271],[8.988,-13.154],[0,0],[-3.135,-1.966],[-0.812,-3.196],[0,0],[0,0],[0,0],[-2.125,8.389],[0,0],[-3.385,6.338],[2.34,3.424],[0,0],[0,0.526],[-2.626,7.634],[0.466,12.246],[37.417,-3.108],[0.175,-4.599]],"v":[[49.849,36.832],[45.911,25.939],[44.474,18.878],[41.563,1.161],[38.853,-29.024],[35.997,-42.869],[11.922,-53.765],[11.099,-67.001],[-0.001,-66.977],[-11.1,-67.001],[-11.922,-53.765],[-34.831,-42.994],[-38.853,-29.024],[-42.564,2.411],[-44.663,19.315],[-45.913,25.939],[-49.849,36.832],[-52.065,54.755],[-0.001,61.927],[52.064,54.755]],"c":true}]},{"i":{"x":0.833,"y":0.833},"o":{"x":0.167,"y":0.167},"t":33,"s":[{"i":[[0.454,14.969],[0.227,3.222],[0,0],[-2.339,3.424],[3.384,6.338],[0,0],[2.124,8.386],[0,0],[0,0],[0,0],[0.813,-3.196],[4.399,-0.803],[0,0],[-8.98,-13.154],[0.237,-4.892],[0,0],[0.186,-8.161],[-0.175,-4.598],[-37.399,-3.105],[-0.466,12.236]],"o":[[-0.26,-8.592],[0,0],[-0.998,-4.892],[8.979,-13.142],[0,0],[-3.135,-1.964],[-0.812,-3.196],[0,0],[0,0],[0,0],[-2.124,8.383],[0,0],[-3.384,6.339],[2.338,3.425],[0,0],[0,0.526],[-0.183,8.063],[0.466,12.246],[37.405,-3.107],[0.175,-4.599]],"v":[[51.587,38.559],[50.639,27.294],[47.649,14.862],[43.229,1.717],[38.834,-29.014],[41.951,-41.887],[13.608,-53.765],[12.018,-64.903],[0,-66.977],[-12.326,-66.014],[-13.148,-52.408],[-40.625,-42.462],[-38.834,-29.014],[-43.228,1.721],[-48.111,14.869],[-51.864,28.411],[-52.889,43.244],[-50.663,61.403],[1.535,69.694],[52.191,60.418]],"c":true}]},{"t":149,"s":[{"i":[[0.03,7.957],[0.028,0.863],[0,0],[-1.818,3.721],[3.384,6.338],[0,0],[1.57,6.457],[0,0],[0,0],[0,0],[1.259,-3.043],[3.389,-1.294],[0,0],[-3.314,-12.992],[2.112,-8.881],[0,0],[1.526,-7.676],[-0.067,-3.749],[-24.996,-0.769],[-0.28,5.59]],"o":[[0.008,-7.73],[0,0],[-0.125,-8.949],[2.779,-5.218],[0,0],[-3.186,-0.646],[-0.778,-3.204],[0,0],[0,0],[0,0],[-1.57,4.028],[0,0],[-2.573,6.685],[0.98,3.991],[0,0],[0,0.526],[-0.416,2.751],[0.212,12.253],[28.954,-2.119],[0.175,-4.599]],"v":[[34.712,38.397],[33.764,25.677],[30.305,13.945],[28.631,-2.596],[26.111,-22.006],[25.947,-45.121],[13.608,-53.765],[12.018,-64.903],[-0.001,-66.977],[-12.326,-66.014],[-13.148,-52.408],[-25.565,-45.26],[-26.111,-22.006],[-27.022,0.481],[-31.37,18.75],[-33.918,31.43],[-35.478,40.495],[-35.328,51.269],[3.008,65.22],[34.579,51.578]],"c":true}]}],"ix":2},"nm":"Path 1","mn":"ADBE Vector Shape - Group","hd":false},{"ty":"mm","mm":4,"nm":"Merge Paths 1","mn":"ADBE Vector Filter - Merge","hd":false},{"ty":"fl","c":{"a":0,"k":[1,0.807843197093,0.666666666667,1],"ix":4},"o":{"a":0,"k":100,"ix":5},"r":1,"bm":0,"nm":"Fill 1","mn":"ADBE Vector Graphic - Fill","hd":false},{"ty":"tr","p":{"a":0,"k":[52.724,67.251],"ix":2},"a":{"a":0,"k":[0,0],"ix":1},"s":{"a":0,"k":[100,100],"ix":3},"r":{"a":0,"k":0,"ix":6},"o":{"a":0,"k":100,"ix":7},"sk":{"a":0,"k":0,"ix":4},"sa":{"a":0,"k":0,"ix":5},"nm":"Transform"}],"nm":"Group 1","np":3,"cix":2,"bm":0,"ix":1,"mn":"ADBE Vector Group","hd":false}],"ip":0,"op":155,"st":0,"bm":0},{"ddd":0,"ind":7,"ty":4,"nm":"Shirt Hand 2","sr":1,"ks":{"o":{"a":0,"k":100,"ix":11},"r":{"a":0,"k":0,"ix":10},"p":{"a":0,"k":[189.25,363.25,0],"ix":2},"a":{"a":0,"k":[0,0,0],"ix":1},"s":{"a":0,"k":[-150,150,100],"ix":6}},"ao":0,"shapes":[{"ty":"gr","it":[{"ind":0,"ty":"sh","ix":1,"ks":{"a":1,"k":[{"i":{"x":0.833,"y":0.833},"o":{"x":0.167,"y":0.167},"t":0,"s":[{"i":[[2.375,0.062],[-0.688,-2.438],[0,0],[-7.5,6.031],[4.906,9.312]],"o":[[-2.375,-0.062],[11.75,6.812],[0,0],[-2.188,-9.75],[-5.156,-14.75]],"v":[[17.188,-171.875],[16.25,-161.5],[44.312,-119.438],[64.062,-132.781],[53.219,-158]],"c":true}]},{"i":{"x":0.833,"y":0.833},"o":{"x":0.167,"y":0.167},"t":65,"s":[{"i":[[7.242,-0.333],[-0.688,-2.438],[0,0],[-7.299,4.062],[4.344,6.319]],"o":[[-2.304,0.025],[7.333,4.904],[0,0],[-1.26,-10.064],[-7.344,-13.306]],"v":[[12.389,-171.889],[15.868,-161.8],[34.033,-129.202],[55.987,-138.812],[46.531,-161.444]],"c":true}]},{"i":{"x":0.833,"y":0.833},"o":{"x":0.167,"y":0.167},"t":106,"s":[{"i":[[10.169,-1.742],[-0.688,-2.438],[0,0],[-8.811,2.424],[3.138,5.924]],"o":[[-2.231,0.268],[5.52,4.888],[0,0],[-0.683,-10.259],[-5.761,-13.068]],"v":[[9.398,-171.897],[15.63,-161.987],[27.279,-135.498],[48.12,-140.543],[41.572,-162.783]],"c":true}]},{"i":{"x":0.833,"y":0.833},"o":{"x":0.167,"y":0.167},"t":149,"s":[{"i":[[13.24,-3.219],[-0.687,-2.438],[0,0],[-10.396,0.707],[1.873,5.51]],"o":[[-2.155,0.524],[3.619,4.87],[0,0],[-0.077,-10.464],[-4.101,-12.818]],"v":[[6.26,-171.906],[15.381,-162.183],[21.989,-141.974],[39.868,-142.36],[36.37,-164.188]],"c":true}]},{"t":150,"s":[{"i":[[13.531,-0.844],[-0.688,-2.438],[0,0],[-10.438,0.625],[1.844,5.5]],"o":[[-2.212,0.138],[1.625,2.438],[0,0],[-0.062,-10.469],[-4.062,-12.812]],"v":[[6.188,-171.906],[15.375,-162.188],[22.469,-142.25],[39.688,-142.406],[36.312,-164.031]],"c":true}]}],"ix":2},"nm":"Path 1","mn":"ADBE Vector Shape - Group","hd":false},{"ty":"st","c":{"a":0,"k":[0.149019996793,0.117646998985,0.2,1],"ix":3},"o":{"a":0,"k":100,"ix":4},"w":{"a":0,"k":0,"ix":5},"lc":1,"lj":1,"ml":4,"bm":0,"nm":"Stroke 1","mn":"ADBE Vector Graphic - Stroke","hd":false},{"ty":"fl","c":{"a":0,"k":[0.447058823529,0.035294117647,0.717647058824,1],"ix":4},"o":{"a":0,"k":100,"ix":5},"r":1,"bm":0,"nm":"Fill 1","mn":"ADBE Vector Graphic - Fill","hd":false},{"ty":"tr","p":{"a":0,"k":[0,0],"ix":2},"a":{"a":0,"k":[0,0],"ix":1},"s":{"a":0,"k":[100,100],"ix":3},"r":{"a":0,"k":0,"ix":6},"o":{"a":0,"k":100,"ix":7},"sk":{"a":0,"k":0,"ix":4},"sa":{"a":0,"k":0,"ix":5},"nm":"Transform"}],"nm":"Shape 1","np":3,"cix":2,"bm":0,"ix":1,"mn":"ADBE Vector Group","hd":false}],"ip":0,"op":150,"st":0,"bm":0},{"ddd":0,"ind":8,"ty":4,"nm":"Shirt Hand","sr":1,"ks":{"o":{"a":0,"k":100,"ix":11},"r":{"a":0,"k":0,"ix":10},"p":{"a":0,"k":[189.25,363.25,0],"ix":2},"a":{"a":0,"k":[0,0,0],"ix":1},"s":{"a":0,"k":[150,150,100],"ix":6}},"ao":0,"shapes":[{"ty":"gr","it":[{"ind":0,"ty":"sh","ix":1,"ks":{"a":1,"k":[{"i":{"x":0.833,"y":0.833},"o":{"x":0.167,"y":0.167},"t":0,"s":[{"i":[[2.375,0.062],[-0.688,-2.438],[0,0],[-7.5,6.031],[4.906,9.312]],"o":[[-2.375,-0.062],[11.75,6.812],[0,0],[-2.188,-9.75],[-5.156,-14.75]],"v":[[17.188,-171.875],[16.25,-161.5],[44.312,-119.438],[64.062,-132.781],[53.219,-158]],"c":true}]},{"i":{"x":0.833,"y":0.833},"o":{"x":0.167,"y":0.167},"t":65,"s":[{"i":[[7.242,-0.333],[-0.688,-2.438],[0,0],[-7.299,4.062],[4.344,6.319]],"o":[[-2.304,0.025],[7.333,4.904],[0,0],[-1.26,-10.064],[-7.344,-13.306]],"v":[[12.389,-171.889],[15.868,-161.8],[34.033,-129.202],[55.987,-138.812],[46.531,-161.444]],"c":true}]},{"i":{"x":0.833,"y":0.833},"o":{"x":0.167,"y":0.167},"t":106,"s":[{"i":[[10.169,-1.742],[-0.688,-2.438],[0,0],[-8.811,2.424],[3.138,5.924]],"o":[[-2.231,0.268],[5.52,4.888],[0,0],[-0.683,-10.259],[-5.761,-13.068]],"v":[[9.398,-171.897],[15.63,-161.987],[27.279,-135.498],[48.12,-140.543],[41.572,-162.783]],"c":true}]},{"i":{"x":0.833,"y":0.833},"o":{"x":0.167,"y":0.167},"t":149,"s":[{"i":[[13.24,-3.219],[-0.687,-2.438],[0,0],[-10.396,0.707],[1.873,5.51]],"o":[[-2.155,0.524],[3.619,4.87],[0,0],[-0.077,-10.464],[-4.101,-12.818]],"v":[[6.26,-171.906],[15.381,-162.183],[21.989,-141.974],[39.868,-142.36],[36.37,-164.188]],"c":true}]},{"t":150,"s":[{"i":[[13.531,-0.844],[-0.688,-2.438],[0,0],[-10.438,0.625],[1.844,5.5]],"o":[[-2.212,0.138],[1.625,2.438],[0,0],[-0.062,-10.469],[-4.062,-12.812]],"v":[[6.188,-171.906],[15.375,-162.188],[22.469,-142.25],[39.688,-142.406],[36.312,-164.031]],"c":true}]}],"ix":2},"nm":"Path 1","mn":"ADBE Vector Shape - Group","hd":false},{"ty":"st","c":{"a":0,"k":[0.149019996793,0.117646998985,0.2,1],"ix":3},"o":{"a":0,"k":100,"ix":4},"w":{"a":0,"k":0,"ix":5},"lc":1,"lj":1,"ml":4,"bm":0,"nm":"Stroke 1","mn":"ADBE Vector Graphic - Stroke","hd":false},{"ty":"fl","c":{"a":0,"k":[0.447058823529,0.035294117647,0.717647058824,1],"ix":4},"o":{"a":0,"k":100,"ix":5},"r":1,"bm":0,"nm":"Fill 1","mn":"ADBE Vector Graphic - Fill","hd":false},{"ty":"tr","p":{"a":0,"k":[0,0],"ix":2},"a":{"a":0,"k":[0,0],"ix":1},"s":{"a":0,"k":[100,100],"ix":3},"r":{"a":0,"k":0,"ix":6},"o":{"a":0,"k":100,"ix":7},"sk":{"a":0,"k":0,"ix":4},"sa":{"a":0,"k":0,"ix":5},"nm":"Transform"}],"nm":"Shape 1","np":3,"cix":2,"bm":0,"ix":1,"mn":"ADBE Vector Group","hd":false}],"ip":0,"op":150,"st":0,"bm":0},{"ddd":0,"ind":9,"ty":4,"nm":"RL","sr":1,"ks":{"o":{"a":0,"k":100,"ix":11},"r":{"a":0,"k":0,"ix":10},"p":{"a":0,"k":[189,269.5,0],"ix":2},"a":{"a":0,"k":[0,0,0],"ix":1},"s":{"a":0,"k":[100,100,100],"ix":6}},"ao":0,"shapes":[{"ty":"gr","it":[{"ind":0,"ty":"sh","ix":1,"ks":{"a":1,"k":[{"i":{"x":0.833,"y":0.833},"o":{"x":0.167,"y":0.167},"t":0,"s":[{"i":[[0,0],[-0.5,-16.5],[0.375,-23.5],[3.375,-26.125],[-24.75,0.5],[-3.75,27],[-3,14.75],[0.25,10.125],[0,0]],"o":[[0,0],[0.5,16.5],[-0.375,23.5],[-2.948,22.816],[28.627,-0.578],[4.5,-13.25],[3,-14.75],[4.375,-13.5],[0,0]],"v":[[5.25,-0.125],[5.625,65],[1.5,120.375],[4.375,212.625],[14.75,238],[27.75,203.25],[44.625,146.125],[45.375,88.25],[75.875,2.125]],"c":true}]},{"t":149,"s":[{"i":[[0,0],[-0.5,-16.5],[0.375,-23.5],[0.5,-23],[-17.75,2],[0.125,13.5],[-3,14.75],[0.25,10.125],[0,0]],"o":[[0,0],[0.5,16.5],[-0.375,23.5],[-0.5,23],[17.75,-2],[-0.125,-13.5],[3,-14.75],[-0.25,-10.125],[0,0]],"v":[[5.25,-0.125],[5.375,48],[4,117.625],[5.125,214.875],[14.75,238],[21.25,200.75],[28.125,154.625],[29.375,83.75],[35.375,0.125]],"c":true}]}],"ix":2},"nm":"Path 1","mn":"ADBE Vector Shape - Group","hd":false},{"ty":"st","c":{"a":0,"k":[0,0,0,1],"ix":3},"o":{"a":0,"k":100,"ix":4},"w":{"a":0,"k":0,"ix":5},"lc":1,"lj":1,"ml":4,"bm":0,"nm":"Stroke 1","mn":"ADBE Vector Graphic - Stroke","hd":false},{"ty":"fl","c":{"a":0,"k":[1,0.807843197093,0.666666666667,1],"ix":4},"o":{"a":0,"k":100,"ix":5},"r":1,"bm":0,"nm":"Fill 1","mn":"ADBE Vector Graphic - Fill","hd":false},{"ty":"tr","p":{"a":0,"k":[0,0],"ix":2},"a":{"a":0,"k":[0,0],"ix":1},"s":{"a":0,"k":[100,100],"ix":3},"r":{"a":0,"k":0,"ix":6},"o":{"a":0,"k":100,"ix":7},"sk":{"a":0,"k":0,"ix":4},"sa":{"a":0,"k":0,"ix":5},"nm":"Transform"}],"nm":"Shape 1","np":3,"cix":2,"bm":0,"ix":1,"mn":"ADBE Vector Group","hd":false}],"ip":0,"op":150,"st":0,"bm":0},{"ddd":0,"ind":10,"ty":4,"nm":"LL","sr":1,"ks":{"o":{"a":0,"k":100,"ix":11},"r":{"a":0,"k":0,"ix":10},"p":{"a":0,"k":[189,269.5,0],"ix":2},"a":{"a":0,"k":[0,0,0],"ix":1},"s":{"a":0,"k":[-100,100,100],"ix":6}},"ao":0,"shapes":[{"ty":"gr","it":[{"ind":0,"ty":"sh","ix":1,"ks":{"a":1,"k":[{"i":{"x":0.833,"y":0.833},"o":{"x":0.167,"y":0.167},"t":0,"s":[{"i":[[0,0],[-0.5,-16.5],[0.375,-23.5],[3.375,-26.125],[-24.75,0.5],[-3.75,27],[-3,14.75],[0.25,10.125],[0,0]],"o":[[0,0],[0.5,16.5],[-0.375,23.5],[-2.948,22.816],[28.627,-0.578],[4.5,-13.25],[3,-14.75],[4.375,-13.5],[0,0]],"v":[[5.25,-0.125],[5.625,65],[1.5,120.375],[4.375,212.625],[14.75,238],[27.75,203.25],[44.625,146.125],[45.375,88.25],[75.875,2.125]],"c":true}]},{"t":149,"s":[{"i":[[0,0],[-0.5,-16.5],[0.375,-23.5],[0.5,-23],[-17.75,2],[0.125,13.5],[-3,14.75],[0.25,10.125],[0,0]],"o":[[0,0],[0.5,16.5],[-0.375,23.5],[-0.5,23],[17.75,-2],[-0.125,-13.5],[3,-14.75],[-0.25,-10.125],[0,0]],"v":[[5.25,-0.125],[5.375,48],[4,117.625],[5.125,214.875],[14.75,238],[21.25,200.75],[28.125,154.625],[29.375,83.75],[35.375,0.125]],"c":true}]}],"ix":2},"nm":"Path 1","mn":"ADBE Vector Shape - Group","hd":false},{"ty":"st","c":{"a":0,"k":[0,0,0,1],"ix":3},"o":{"a":0,"k":100,"ix":4},"w":{"a":0,"k":0,"ix":5},"lc":1,"lj":1,"ml":4,"bm":0,"nm":"Stroke 1","mn":"ADBE Vector Graphic - Stroke","hd":false},{"ty":"fl","c":{"a":0,"k":[1,0.807843197093,0.666666666667,1],"ix":4},"o":{"a":0,"k":100,"ix":5},"r":1,"bm":0,"nm":"Fill 1","mn":"ADBE Vector Graphic - Fill","hd":false},{"ty":"tr","p":{"a":0,"k":[0,0],"ix":2},"a":{"a":0,"k":[0,0],"ix":1},"s":{"a":0,"k":[100,100],"ix":3},"r":{"a":0,"k":0,"ix":6},"o":{"a":0,"k":100,"ix":7},"sk":{"a":0,"k":0,"ix":4},"sa":{"a":0,"k":0,"ix":5},"nm":"Transform"}],"nm":"Shape 1","np":3,"cix":2,"bm":0,"ix":1,"mn":"ADBE Vector Group","hd":false}],"ip":0,"op":150,"st":0,"bm":0},{"ddd":0,"ind":11,"ty":4,"nm":"RH","sr":1,"ks":{"o":{"a":0,"k":100,"ix":11},"r":{"a":0,"k":0,"ix":10},"p":{"a":0,"k":[189,269.5,0],"ix":2},"a":{"a":0,"k":[0,0,0],"ix":1},"s":{"a":0,"k":[100,100,100],"ix":6}},"ao":0,"shapes":[{"ty":"gr","it":[{"ind":0,"ty":"sh","ix":1,"ks":{"a":1,"k":[{"i":{"x":0.833,"y":0.833},"o":{"x":0.167,"y":0.167},"t":0,"s":[{"i":[[3.75,6.25],[0,0],[-1,-4.5],[-4.375,-4.375],[-2.625,-11],[0.5,-6.875],[-2.875,-0.125],[-1.375,0.25],[3.125,-8.5],[-11,7.75],[1.25,16.75],[3.125,5.25],[3.875,24.875]],"o":[[-4.375,2.125],[0,0],[1,4.5],[-2.125,7],[2.625,11],[-0.5,6.875],[2.875,0.125],[1.375,-0.25],[-3.125,8.5],[11,-7.75],[11.625,-20],[-0.375,-6.125],[-3.875,-24.875]],"v":[[64.75,-153.25],[49.875,-143.375],[61.125,-99.375],[77,-73],[86.75,-26.625],[82.625,-6.75],[83.75,10.25],[87.25,0.125],[89.75,10.125],[93.25,19.625],[103.25,-25.5],[98.75,-85.125],[94.375,-106.125]],"c":true}]},{"t":149,"s":[{"i":[[7.75,-0.25],[0,0],[-1,-4.5],[-4.375,-4.375],[-2.625,-11],[0.5,-6.875],[-2.875,-0.125],[-1.375,0.25],[3.125,-8.5],[-11,7.75],[1.25,16.75],[3.125,5.25],[1.798,25.111]],"o":[[-4.375,2.125],[0,0],[1,4.5],[-2.125,7],[-4.5,2.5],[-0.5,6.875],[2.875,0.125],[1.375,-0.25],[-3.125,8.5],[11,-7.75],[-0.25,-12],[-0.375,-6.125],[-3.625,-50.625]],"v":[[32.75,-163.375],[28.375,-153.75],[35.625,-107.5],[44.25,-67.25],[52,-13.625],[46.625,2.125],[47.5,14],[52.25,5.25],[50.625,16.25],[53.75,23.875],[65.5,-23],[59.5,-79],[58.75,-119.25]],"c":true}]}],"ix":2},"nm":"Path 1","mn":"ADBE Vector Shape - Group","hd":false},{"ty":"st","c":{"a":0,"k":[0,0,0,1],"ix":3},"o":{"a":0,"k":100,"ix":4},"w":{"a":0,"k":0,"ix":5},"lc":1,"lj":1,"ml":4,"bm":0,"nm":"Stroke 1","mn":"ADBE Vector Graphic - Stroke","hd":false},{"ty":"fl","c":{"a":0,"k":[1,0.807843197093,0.666666666667,1],"ix":4},"o":{"a":0,"k":100,"ix":5},"r":1,"bm":0,"nm":"Fill 1","mn":"ADBE Vector Graphic - Fill","hd":false},{"ty":"tr","p":{"a":0,"k":[0,0],"ix":2},"a":{"a":0,"k":[0,0],"ix":1},"s":{"a":0,"k":[100,100],"ix":3},"r":{"a":0,"k":0,"ix":6},"o":{"a":0,"k":100,"ix":7},"sk":{"a":0,"k":0,"ix":4},"sa":{"a":0,"k":0,"ix":5},"nm":"Transform"}],"nm":"Shape 1","np":3,"cix":2,"bm":0,"ix":1,"mn":"ADBE Vector Group","hd":false}],"ip":0,"op":150,"st":0,"bm":0},{"ddd":0,"ind":12,"ty":4,"nm":"LH","sr":1,"ks":{"o":{"a":0,"k":100,"ix":11},"r":{"a":0,"k":0,"ix":10},"p":{"a":0,"k":[189,269.5,0],"ix":2},"a":{"a":0,"k":[0,0,0],"ix":1},"s":{"a":0,"k":[-100,100,100],"ix":6}},"ao":0,"shapes":[{"ty":"gr","it":[{"ind":0,"ty":"sh","ix":1,"ks":{"a":1,"k":[{"i":{"x":0.833,"y":0.833},"o":{"x":0.167,"y":0.167},"t":0,"s":[{"i":[[3.75,6.25],[0,0],[-1,-4.5],[-4.375,-4.375],[-2.625,-11],[0.5,-6.875],[-2.875,-0.125],[-1.375,0.25],[3.125,-8.5],[-11,7.75],[1.25,16.75],[3.125,5.25],[3.875,24.875]],"o":[[-4.375,2.125],[0,0],[1,4.5],[-2.125,7],[2.625,11],[-0.5,6.875],[2.875,0.125],[1.375,-0.25],[-3.125,8.5],[11,-7.75],[11.625,-20],[-0.375,-6.125],[-3.875,-24.875]],"v":[[64.75,-153.25],[49.875,-143.375],[61.125,-99.375],[77,-73],[86.75,-26.625],[82.625,-6.75],[83.75,10.25],[87.25,0.125],[89.75,10.125],[93.25,19.625],[103.25,-25.5],[98.75,-85.125],[94.375,-106.125]],"c":true}]},{"t":149,"s":[{"i":[[7.75,-0.25],[0,0],[-1,-4.5],[-4.375,-4.375],[-2.625,-11],[0.5,-6.875],[-2.875,-0.125],[-1.375,0.25],[3.125,-8.5],[-11,7.75],[1.25,16.75],[3.125,5.25],[1.798,25.111]],"o":[[-4.375,2.125],[0,0],[1,4.5],[-2.125,7],[-4.5,2.5],[-0.5,6.875],[2.875,0.125],[1.375,-0.25],[-3.125,8.5],[11,-7.75],[-0.25,-12],[-0.375,-6.125],[-3.625,-50.625]],"v":[[32.75,-163.375],[28.375,-153.75],[35.625,-107.5],[44.25,-67.25],[52,-13.625],[46.625,2.125],[47.5,14],[52.25,5.25],[50.625,16.25],[53.75,23.875],[65.5,-23],[59.5,-79],[58.75,-119.25]],"c":true}]}],"ix":2},"nm":"Path 1","mn":"ADBE Vector Shape - Group","hd":false},{"ty":"st","c":{"a":0,"k":[0,0,0,1],"ix":3},"o":{"a":0,"k":100,"ix":4},"w":{"a":0,"k":0,"ix":5},"lc":1,"lj":1,"ml":4,"bm":0,"nm":"Stroke 1","mn":"ADBE Vector Graphic - Stroke","hd":false},{"ty":"fl","c":{"a":0,"k":[1,0.807843197093,0.666666666667,1],"ix":4},"o":{"a":0,"k":100,"ix":5},"r":1,"bm":0,"nm":"Fill 1","mn":"ADBE Vector Graphic - Fill","hd":false},{"ty":"tr","p":{"a":0,"k":[0,0],"ix":2},"a":{"a":0,"k":[0,0],"ix":1},"s":{"a":0,"k":[100,100],"ix":3},"r":{"a":0,"k":0,"ix":6},"o":{"a":0,"k":100,"ix":7},"sk":{"a":0,"k":0,"ix":4},"sa":{"a":0,"k":0,"ix":5},"nm":"Transform"}],"nm":"Shape 1","np":3,"cix":2,"bm":0,"ix":1,"mn":"ADBE Vector Group","hd":false}],"ip":0,"op":150,"st":0,"bm":0},{"ddd":0,"ind":13,"ty":4,"nm":"2 Back Hair Outlines","sr":1,"ks":{"o":{"a":0,"k":100,"ix":11},"r":{"a":0,"k":0,"ix":10},"p":{"a":0,"k":[189.002,70.31,0],"ix":2},"a":{"a":0,"k":[24.092,28.083,0],"ix":1},"s":{"a":1,"k":[{"i":{"x":[0.833,0.833,0.833],"y":[0.833,0.833,0.833]},"o":{"x":[0.167,0.167,0.167],"y":[0.167,0.167,0.167]},"t":0,"s":[150,150,100]},{"t":63.1357421875,"s":[136.631,150,100]}],"ix":6}},"ao":0,"shapes":[{"ty":"gr","it":[{"ind":0,"ty":"sh","ix":1,"ks":{"a":0,"k":{"i":[[0.906,9.787],[13.44,-0.012],[1.409,-15.211],[0.722,-7.354],[-1.074,1.8],[-4.918,-1.138]],"o":[[-1.409,-15.211],[-13.439,-0.012],[-0.906,9.787],[4.917,-1.138],[1.074,1.8],[-0.723,-7.354]],"v":[[20.94,-4.793],[-0.001,-26.946],[-20.255,-5.168],[-22.196,30.069],[-0.001,26.033],[21.647,28.194]],"c":true},"ix":2},"nm":"Path 1","mn":"ADBE Vector Shape - Group","hd":false},{"ty":"mm","mm":4,"nm":"Merge Paths 1","mn":"ADBE Vector Filter - Merge","hd":false},{"ty":"fl","c":{"a":0,"k":[0.149019607843,0.149019607843,0.149019607843,1],"ix":4},"o":{"a":0,"k":100,"ix":5},"r":1,"bm":0,"nm":"Fill 1","mn":"ADBE Vector Graphic - Fill","hd":false},{"ty":"tr","p":{"a":0,"k":[24.092,28.083],"ix":2},"a":{"a":0,"k":[0,0],"ix":1},"s":{"a":0,"k":[100,100],"ix":3},"r":{"a":0,"k":0,"ix":6},"o":{"a":0,"k":100,"ix":7},"sk":{"a":0,"k":0,"ix":4},"sa":{"a":0,"k":0,"ix":5},"nm":"Transform"}],"nm":"Group 1","np":3,"cix":2,"bm":0,"ix":1,"mn":"ADBE Vector Group","hd":false}],"ip":0,"op":155,"st":11,"bm":0},{"ddd":0,"ind":14,"ty":4,"nm":"Shape Layer 7","sr":1,"ks":{"o":{"a":0,"k":50,"ix":11},"r":{"a":0,"k":0,"ix":10},"p":{"a":0,"k":[189,501.905,0],"ix":2},"a":{"a":0,"k":[55.609,262.938,0],"ix":1},"s":{"a":1,"k":[{"i":{"x":[0.681,0.668,0.667],"y":[0.784,0.64,1]},"o":{"x":[0.167,0.167,0.167],"y":[0.167,0.167,0]},"t":0,"s":[116.204,112.627,100]},{"i":{"x":[0.833,0.833,0.833],"y":[0.833,0.833,1]},"o":{"x":[0.33,0.331,0.333],"y":[0.884,-0.878,0]},"t":65.661,"s":[80.073,106.159,100]},{"t":149,"s":[68.594,109.296,100]}],"ix":6}},"ao":0,"shapes":[{"ty":"gr","it":[{"d":1,"ty":"el","s":{"a":0,"k":[101.826,15.84],"ix":2},"p":{"a":0,"k":[0,0],"ix":3},"nm":"Ellipse Path 1","mn":"ADBE Vector Shape - Ellipse","hd":false},{"ty":"st","c":{"a":0,"k":[0.968627989526,0.145097994337,0.521568986481,1],"ix":3},"o":{"a":0,"k":100,"ix":4},"w":{"a":0,"k":0,"ix":5},"lc":1,"lj":1,"ml":4,"bm":0,"nm":"Stroke 1","mn":"ADBE Vector Graphic - Stroke","hd":false},{"ty":"fl","c":{"a":0,"k":[0.898039215686,0.898039215686,0.898039215686,1],"ix":4},"o":{"a":0,"k":100,"ix":5},"r":1,"bm":0,"nm":"Fill 1","mn":"ADBE Vector Graphic - Fill","hd":false},{"ty":"tr","p":{"a":0,"k":[55.609,262.938],"ix":2},"a":{"a":0,"k":[0,0],"ix":1},"s":{"a":0,"k":[100,100],"ix":3},"r":{"a":0,"k":0,"ix":6},"o":{"a":0,"k":100,"ix":7},"sk":{"a":0,"k":0,"ix":4},"sa":{"a":0,"k":0,"ix":5},"nm":"Transform"}],"nm":"Ellipse 1","np":3,"cix":2,"bm":0,"ix":1,"mn":"ADBE Vector Group","hd":false}],"ip":0,"op":155,"st":0,"bm":0}],"markers":[]}